pyvectordb/__init__.py
pyvectordb/chromadb/__init__.py
pyvectordb/chromadb/distance.py
pyvectordb/distance_function.py
pyvectordb/driver.py
pyvectordb/pgvector/__init__.py
pyvectordb/pgvector/model.py
pyvectordb/qdrant/__init__.py
pyvectordb/vector.py
pyvectordb/vector_distance.py
pyvectordb-0.1.7.1.dist-info/LICENSE
pyvectordb-0.1.7.1.dist-info/METADATA
pyvectordb-0.1.7.1.dist-info/WHEEL
pyvectordb-0.1.7.1.dist-info/RECORD
