Metadata-Version: 2.1
Name: pyvectordb
Version: 0.1.7.1
Summary: Simple Wrapper for vector database in Python with minimal support for CRUD and retrieve.
Home-page: https://github.com/rizquuula/pyvectordb
Author: M Razif Rizqullah
Author-email: razifrizqullah@gmail.com
Requires-Python: >=3.10,<4.0
Classifier: Programming Language :: Python :: 3
Classifier: Programming Language :: Python :: 3.10
Classifier: Programming Language :: Python :: 3.11
Classifier: Programming Language :: Python :: 3.12
Classifier: Programming Language :: Python :: 3.13
Provides-Extra: all
Provides-Extra: chromadb
Provides-Extra: dev
Provides-Extra: pgvector
Provides-Extra: qdrant
Requires-Dist: chromadb (==0.5.20) ; extra == "chromadb" or extra == "dev" or extra == "all"
Requires-Dist: pgvector (>=0.3.5,<0.4.0) ; extra == "pgvector" or extra == "dev" or extra == "all"
Requires-Dist: psycopg2-binary (>=2.9.10,<3.0.0) ; extra == "pgvector" or extra == "dev" or extra == "all"
Requires-Dist: pytest (>=8.3.3,<9.0.0) ; extra == "dev"
Requires-Dist: qdrant-client (>=1.12.0,<2.0.0) ; extra == "qdrant" or extra == "dev" or extra == "all"
Requires-Dist: sqlalchemy (>=2.0.36,<3.0.0) ; extra == "pgvector" or extra == "dev" or extra == "all"
Project-URL: Repository, https://github.com/rizquuula/pyvectordb
